json4tree/__init__.py
json4tree/__main__.py
json4tree-1.0.2.dist-info/LICENSE
json4tree-1.0.2.dist-info/METADATA
json4tree-1.0.2.dist-info/WHEEL
json4tree-1.0.2.dist-info/top_level.txt
json4tree-1.0.2.dist-info/RECORD
